MANIFEST.in
setup.cfg
setup.py
modviz/__init__.py
modviz/cli.py
modviz/modviz.py
modviz.egg-info/PKG-INFO
modviz.egg-info/SOURCES.txt
modviz.egg-info/dependency_links.txt
modviz.egg-info/entry_points.txt
modviz.egg-info/pbr.json
modviz.egg-info/top_level.txt
modviz/static/template.html