Metadata-Version: 1.1
Name: modviz
Version: 0.2.0
Summary: Modviz lets you visualize your module dependencies.
Home-page: https://github.com/Bogdanp/modviz
Author: Bogdan Popa
Author-email: popa.bogdanp@gmail.com
License: UNKNOWN
Keywords: visualization
Platform: UNKNOWN
Classifier: Development Status :: 3 - Alpha
Classifier: License :: OSI Approved :: MIT License
